hddm_s.cpython-310-i386-linux-gnu.so
hddm_s/event.xml
hddm_s-2.0.196.dist-info/LICENSE
hddm_s-2.0.196.dist-info/WHEEL
hddm_s-2.0.196.dist-info/top_level.txt
hddm_s-2.0.196.dist-info/RECORD
hddm_s-2.0.196.dist-info/METADATA
