Metadata-Version: 2.1
Name: hddm_s
Version: 2.0.196
Summary: methods for reading and writing GlueX simulated event data
Home-page: https://github.com/rjones30/hddm_s
Author: Richard T. Jones
Author-email: "Richard T. Jones" <richard.t.jones@uconn.edu>
Maintainer-email: "Richard T. Jones" <richard.t.jones@uconn.edu>
License: MIT License
Project-URL: Homepage, https://github.com/rjones30/hddm_s
Project-URL: Documentation, https://github.com/rjones30/hddm_s
Project-URL: Repository, https://github.com/rjones30/hddm_s
Project-URL: Issues, https://github.com/rjones30/hddm_s/issues
Project-URL: Changelog, https://github.com/rjones30/hddm_s/issues/main/CHANGELOG.md
Keywords: hddm,GlueX,Gluex,gluex,hdgeant4,hdgeant
Classifier: Development Status :: 4 - Beta
Classifier: Intended Audience :: Science/Research
Classifier: Topic :: Scientific/Engineering :: Physics
Classifier: License :: OSI Approved :: MIT License
Classifier: Programming Language :: Python
Requires-Python: >=3.6
License-File: LICENSE
